{
  "平台用户管理": "プラットフォームユーザー管理",
  "管理平台级用户账号，包括创建、编辑、启用/禁用、重置密码等操作": "プラットフォームユーザーアカウントの作成、編集、有効/無効、パスワードリセットなどの操作を管理します",
  "请输入用户名或显示名": "ユーザー名または表示名を入力",
  "请选择状态": "ステータスを選択",
  "请选择角色": "ロールを選択",
  "高级查询": "詳細検索",
  "收起": "閉じる",
  "用户名": "ユーザー名",
  "显示名": "表示名",
  "邮箱": "メール",
  "手机": "電話",
  "角色": "ロール",
  "新增用户": "ユーザー作成",
  "编辑用户": "ユーザー編集",
  "用户详情": "ユーザー詳細",
  "密码": "パスワード",
  "请输入用户名": "ユーザー名を入力",
  "请输入密码": "パスワードを入力",
  "请输入显示名": "表示名を入力",
  "用户名长度 3-50 个字符": "ユーザー名は3-50文字",
  "用户名仅允许字母、数字和下划线": "ユーザー名は英数字とアンダースコアのみ",
  "用户名已存在": "ユーザー名は既に存在します",
  "密码长度至少 6 个字符": "パスワードは6文字以上",
  "显示名长度 2-50 个字符": "表示名は2-50文字",
  "请输入正确的邮箱地址": "正しいメールアドレスを入力してください",
  "邮箱长度不超过 100 个字符": "メールは100文字以内",
  "手机号长度不超过 20 个字符": "電話番号は20文字以内",
  "确认启用用户 {name}": "ユーザー {name} を有効にしますか",
  "确认禁用用户 {name}": "ユーザー {name} を無効にしますか",
  "确认重置用户 {name} 的密码": "ユーザー {name} のパスワードをリセットしますか",
  "确认批量启用选中用户": "選択したユーザーを一括有効にしますか",
  "确认批量禁用选中用户": "選択したユーザーを一括無効にしますか",
  "重置密码成功": "パスワードリセット成功",
  "批量启用成功": "一括有効化成功",
  "批量禁用成功": "一括無効化成功",
  "批量启用": "一括有効化",
  "批量禁用": "一括無効化",
  "确认删除 {name}": "{name} を削除しますか",
  "最后登录": "最終ログイン",
  "备注": "備考",
  "查询": null,
  "重置": null,
  "新增": null,
  "编辑": null,
  "删除": null,
  "查看": null,
  "启用": null,
  "禁用": null,
  "确定": null,
  "取消": null,
  "操作": null,
  "ID": null,
  "状态": null,
  "创建时间": null,
  "更新时间": null,
  "已启用": null,
  "已禁用": null,
  "全部": null,
  "暂无数据": null,
  "功能说明": null,
  "操作指南": null,
  "创建成功": null,
  "更新成功": null,
  "删除成功": null,
  "启用成功": null,
  "禁用成功": null,
  "重置密码": null
}
